adlmagics/__init__.py
adlmagics/adlmagics_main.py
adlmagics/exceptions.py
adlmagics/magics/__init__.py
adlmagics/magics/magic_base.py
adlmagics/magics/adla/__init__.py
adlmagics/magics/adla/adla_accounts_listing_magic.py
adlmagics/magics/adla/adla_consts.py
adlmagics/magics/adla/adla_job_submission_magic.py
adlmagics/magics/adla/adla_job_viewing_magic.py
adlmagics/magics/adla/adla_jobs_listing_magic.py
adlmagics/magics/adla/adla_magic_base.py
adlmagics/magics/adls/__init__.py
adlmagics/magics/adls/adls_accounts_listing_magic.py
adlmagics/magics/adls/adls_file_sampling_magic.py
adlmagics/magics/adls/adls_files_listing_magic.py
adlmagics/magics/adls/adls_folders_listing_magic.py
adlmagics/magics/adls/adls_magic_base.py
adlmagics/magics/azure/__init__.py
adlmagics/magics/azure/azure_login_magic.py
adlmagics/magics/azure/azure_logout_magic.py
adlmagics/magics/azure/azure_magic_base.py
adlmagics/magics/session/__init__.py
adlmagics/magics/session/session_list_magic.py
adlmagics/magics/session/session_magic_base.py
adlmagics/models/__init__.py
adlmagics/models/adla_account.py
adlmagics/models/adla_job.py
adlmagics/models/adla_job_submission.py
adlmagics/models/adls_account.py
adlmagics/models/adls_file.py
adlmagics/models/adls_folder.py
adlmagics/services/__init__.py
adlmagics/services/adla_service_sdk_impl.py
adlmagics/services/adls_service_sdk_impl.py
adlmagics/services/azure_token_service.py
adlmagics/services/session_manager.py
adlmagics-0.0.1a2.dist-info/METADATA
adlmagics-0.0.1a2.dist-info/RECORD
adlmagics-0.0.1a2.dist-info/WHEEL
adlmagics-0.0.1a2.dist-info/top_level.txt
