Metadata-Version: 2.1
Name: adlmagics
Version: 0.0.1a2
Summary: Azure Data Lake management magics for Jupyter Notebook
Home-page: https://github.com/Azure/Azure-Data-Service-Notebook
Author: Vincent Feng
Author-email: ivincentfeng@live.com
License: MIT
Download-URL: https://github.com/Azure/Azure-Data-Service-Notebook
Platform: UNKNOWN
Classifier: Development Status :: 3 - Alpha
Classifier: Framework :: Jupyter
Classifier: Intended Audience :: Science/Research
Classifier: License :: OSI Approved :: MIT License
Classifier: Natural Language :: English
Classifier: Programming Language :: Python :: 3.6
Classifier: Operating System :: OS Independent
Requires-Dist: ipython (>=5.3.0)
Requires-Dist: notebook (>=5.0.0)
Requires-Dist: ipykernel (>=4.6.1)
Requires-Dist: pandas (>=0.20.1)
Requires-Dist: numpy
Requires-Dist: adal
Requires-Dist: azure-mgmt-resource
Requires-Dist: azure-mgmt-datalake-analytics (>=0.4.0)
Requires-Dist: azure-mgmt-datalake-store
Requires-Dist: azure-datalake-store
